[{"x":0,"y":0,"w":2,"h":12,"i":"0","ref":"babo","api":"/api/systemstat","comp_type":"card-system-state","title":"system info","refresh_period":10000,"scroll_height":160,"moved":false},{"x":0,"y":12,"w":2,"h":8,"i":"1","api":"/api/diskstat","comp_type":"card-state-list","title":"disk info","refresh_period":10000,"scroll_height":160,"moved":false},{"x":2,"y":7,"w":2,"h":13,"i":"2","api":"/api/fsstat","comp_type":"card-state-list","title":"file system info","refresh_period":10000,"scroll_height":160,"moved":false},{"x":4,"y":15,"w":8,"h":6,"i":"3","api":"/api/networkinterfaces","comp_type":"card-state-table","title":"network interface","refresh_period":-1,"scroll_height":160,"moved":false},{"x":2,"y":0,"w":2,"h":7,"i":"4","api":"/api/netstat","comp_type":"card-state-list","title":"netstat","refresh_period":-1,"scroll_height":160,"moved":false},{"x":4,"y":0,"w":8,"h":8,"i":"5","api":"/api/processess","comp_type":"card-state-table","title":"process info","refresh_period":-1,"scroll_height":250,"moved":false},{"x":4,"y":8,"w":8,"h":7,"i":"6","api":"/api/connectstat","comp_type":"card-state-table","title":"connections","refresh_period":-1,"scroll_height":160,"moved":false},{"x":0,"y":21,"w":8,"h":7,"i":"7","api":"/api/services","comp_type":"card-state-table","title":"services","refresh_period":5000,"scroll_height":160,"moved":false}]
